{
  "schemaVersion": 1,
  "id": "vanilla-hammers",
  "version": "1.5.0",

  "name": "Vanilla Hammers",
  "description": "Adds a ton of new hammers to the game!",
  "authors": [
    "Draylar"
  ],

  "license": "GPLv3",
  "icon": "assets/vanilla-hammers/icon.png",

  "environment": "*",
  "entrypoints": {
    "main": [
      "com.github.draylar.vh.VanillaHammers"
    ],
    "modmenu": [
      "com.github.draylar.vh.ModMenuIntegration"
    ],
    "dynagear:equipment_types": [
      "com.github.draylar.vh.compat.DynaGearCompat"
    ]
  },
  "mixins": [
    "vanillahammers.mixin.json"
  ],
  "requires": {
    "fabricloader": "=>0.4.0",
    "fabric": "*"
  }
}
